envix/__init__.py
envix/envname.py
envix/exception.py
envix/path.py
envix/pattern.py
envix/types.py
envix/cli/__init__.py
envix/cli/__main__.py
envix/cli/app.py
envix/cli/default.py
envix/cli/field.py
envix/cli/commands/__init__.py
envix/cli/commands/config.py
envix/cli/commands/config_edit.py
envix/cli/commands/config_list.py
envix/cli/commands/config_schema.py
envix/cli/commands/export.py
envix/cli/commands/inject.py
envix/config/__init__.py
envix/config/config.py
envix/config/v1/__init__.py
envix/config/v1/config.py
envix/config/v1/envix_v1.py
envix/config/v1/envs/__init__.py
envix/config/v1/envs/_common.py
envix/config/v1/envs/file_envs_v1.py
envix/config/v1/envs/google_cloud_secret_manager_envs_v1.py
envix/config/v1/envs/local_envs_v1.py
envix/config/v1/envs/raw_envs_v1.py
envix/loader/__init__.py
envix/loader/v1_loader.py
envix-0.2.9.dist-info/METADATA
envix-0.2.9.dist-info/WHEEL
envix-0.2.9.dist-info/entry_points.txt
envix-0.2.9.dist-info/RECORD
